MANIFEST.in
setup.py
cthreeML/ModelInterface.h
cthreeML/__init__.py
cthreeML/pyToCppModelInterface.cxx
cthreeML/pyToCppModelInterface.h
cthreeML/pyToCppModelInterfaceCache.cxx
cthreeML/pyToCppModelInterfaceCache.h
cthreeML.egg-info/PKG-INFO
cthreeML.egg-info/SOURCES.txt
cthreeML.egg-info/dependency_links.txt
cthreeML.egg-info/top_level.txt