Metadata-Version: 1.1
Name: cthreeML
Version: 1.0.2
Summary: The C/C++ bridge for the Multi-Mission Maximum Likelihood framework (github.com/giacomov/3ML)
Home-page: https://github.com/giacomov/cthreeML
Author: Giacomo Vianello
Author-email: giacomo.vianello@gmail.com
License: BSD-3
Download-URL: https://github.com/giacomov/cthreeML/archive/1.0.2
Keywords: Likelihood,Multi-mission,3ML,HAWC,Fermi,HESS,joint,fit,bayesian,multi-wavelength
Platform: UNKNOWN
